{
  "name": "pyrope",
  "word": "identifier",
  "rules": {
    "start": {
      "type": "SEQ",
      "members": [
        {
          "type": "CHOICE",
          "members": [
            {
              "type": "SYMBOL",
              "name": "_newline"
            },
            {
              "type": "BLANK"
            }
          ]
        },
        {
          "type": "CHOICE",
          "members": [
            {
              "type": "SEQ",
              "members": [
                {
                  "type": "STRING",
                  "value": "|"
                },
                {
                  "type": "SYMBOL",
                  "name": "lambda_def_constrains"
                },
                {
                  "type": "SYMBOL",
                  "name": "_newline"
                }
              ]
            },
            {
              "type": "BLANK"
            }
          ]
        },
        {
          "type": "REPEAT",
          "content": {
            "type": "SYMBOL",
            "name": "stmt"
          }
        }
      ]
    },
    "stmt": {
      "type": "SEQ",
      "members": [
        {
          "type": "CHOICE",
          "members": [
            {
              "type": "SYMBOL",
              "name": "if_stmt"
            },
            {
              "type": "SYMBOL",
              "name": "while_stmt"
            },
            {
              "type": "SYMBOL",
              "name": "for_stmt"
            },
            {
              "type": "SYMBOL",
              "name": "ass_fcall_stmt"
            },
            {
              "type": "SYMBOL",
              "name": "ctrl_stmt"
            }
          ]
        },
        {
          "type": "CHOICE",
          "members": [
            {
              "type": "SYMBOL",
              "name": "gate_stmt"
            },
            {
              "type": "BLANK"
            }
          ]
        },
        {
          "type": "SYMBOL",
          "name": "_newline"
        }
      ]
    },
    "gate_stmt": {
      "type": "SEQ",
      "members": [
        {
          "type": "CHOICE",
          "members": [
            {
              "type": "STRING",
              "value": "when"
            },
            {
              "type": "STRING",
              "value": "unless"
            }
          ]
        },
        {
          "type": "SYMBOL",
          "name": "expr_entry"
        }
      ]
    },
    "if_stmt": {
      "type": "SEQ",
      "members": [
        {
          "type": "CHOICE",
          "members": [
            {
              "type": "STRING",
              "value": "unique"
            },
            {
              "type": "BLANK"
            }
          ]
        },
        {
          "type": "STRING",
          "value": "if"
        },
        {
          "type": "SYMBOL",
          "name": "expr_entry"
        },
        {
          "type": "SYMBOL",
          "name": "scope_stmt"
        },
        {
          "type": "REPEAT",
          "content": {
            "type": "SYMBOL",
            "name": "if_elif"
          }
        },
        {
          "type": "CHOICE",
          "members": [
            {
              "type": "SYMBOL",
              "name": "else_line"
            },
            {
              "type": "BLANK"
            }
          ]
        }
      ]
    },
    "if_elif": {
      "type": "SEQ",
      "members": [
        {
          "type": "STRING",
          "value": "elif"
        },
        {
          "type": "SYMBOL",
          "name": "expr_entry"
        },
        {
          "type": "SYMBOL",
          "name": "scope_stmt"
        }
      ]
    },
    "else_line": {
      "type": "SEQ",
      "members": [
        {
          "type": "STRING",
          "value": "else"
        },
        {
          "type": "SYMBOL",
          "name": "scope_stmt"
        }
      ]
    },
    "while_stmt": {
      "type": "SEQ",
      "members": [
        {
          "type": "STRING",
          "value": "while"
        },
        {
          "type": "SYMBOL",
          "name": "expr_entry"
        },
        {
          "type": "SYMBOL",
          "name": "scope_stmt"
        }
      ]
    },
    "for_stmt": {
      "type": "SEQ",
      "members": [
        {
          "type": "STRING",
          "value": "for"
        },
        {
          "type": "SYMBOL",
          "name": "identifier"
        },
        {
          "type": "SYMBOL",
          "name": "in_range"
        },
        {
          "type": "SYMBOL",
          "name": "scope_stmt"
        }
      ]
    },
    "ctrl_stmt": {
      "type": "CHOICE",
      "members": [
        {
          "type": "STRING",
          "value": "continue"
        },
        {
          "type": "STRING",
          "value": "break"
        },
        {
          "type": "STRING",
          "value": "return"
        }
      ]
    },
    "ass_fcall_stmt": {
      "type": "SEQ",
      "members": [
        {
          "type": "CHOICE",
          "members": [
            {
              "type": "SYMBOL",
              "name": "assign_attr"
            },
            {
              "type": "BLANK"
            }
          ]
        },
        {
          "type": "SYMBOL",
          "name": "variable_base"
        },
        {
          "type": "SEQ",
          "members": [
            {
              "type": "CHOICE",
              "members": [
                {
                  "type": "SYMBOL",
                  "name": "assignment_cont"
                },
                {
                  "type": "SYMBOL",
                  "name": "expr_seq1"
                }
              ]
            },
            {
              "type": "REPEAT",
              "content": {
                "type": "SYMBOL",
                "name": "fcall_pipe"
              }
            }
          ]
        }
      ]
    },
    "ass_fcall_func_cont": {
      "type": "SEQ",
      "members": [
        {
          "type": "SYMBOL",
          "name": "fcall_args"
        },
        {
          "type": "CHOICE",
          "members": [
            {
              "type": "SYMBOL",
              "name": "fcall_pipe"
            },
            {
              "type": "BLANK"
            }
          ]
        }
      ]
    },
    "fcall_pipe": {
      "type": "SEQ",
      "members": [
        {
          "type": "STRING",
          "value": "|>"
        },
        {
          "type": "SYMBOL",
          "name": "variable_base"
        },
        {
          "type": "SYMBOL",
          "name": "fcall_args"
        }
      ]
    },
    "assign_attr": {
      "type": "CHOICE",
      "members": [
        {
          "type": "SEQ",
          "members": [
            {
              "type": "SYMBOL",
              "name": "expr_attr"
            },
            {
              "type": "STRING",
              "value": "let"
            },
            {
              "type": "SYMBOL",
              "name": "let_attr"
            }
          ]
        },
        {
          "type": "STRING",
          "value": "mut"
        },
        {
          "type": "STRING",
          "value": "set"
        },
        {
          "type": "STRING",
          "value": "var"
        }
      ]
    },
    "let_attr": {
      "type": "CHOICE",
      "members": [
        {
          "type": "SYMBOL",
          "name": "pipe_check"
        },
        {
          "type": "SYMBOL",
          "name": "repipe_check"
        },
        {
          "type": "STRING",
          "value": "type"
        }
      ]
    },
    "assignment_cont": {
      "type": "SEQ",
      "members": [
        {
          "type": "CHOICE",
          "members": [
            {
              "type": "SYMBOL",
              "name": "typecase"
            },
            {
              "type": "BLANK"
            }
          ]
        },
        {
          "type": "CHOICE",
          "members": [
            {
              "type": "STRING",
              "value": "="
            },
            {
              "type": "STRING",
              "value": ":="
            },
            {
              "type": "STRING",
              "value": "+="
            },
            {
              "type": "STRING",
              "value": "-="
            },
            {
              "type": "STRING",
              "value": "++="
            },
            {
              "type": "STRING",
              "value": "|="
            },
            {
              "type": "STRING",
              "value": "&="
            },
            {
              "type": "STRING",
              "value": "^="
            },
            {
              "type": "STRING",
              "value": "*="
            },
            {
              "type": "STRING",
              "value": "/="
            },
            {
              "type": "STRING",
              "value": "or="
            },
            {
              "type": "STRING",
              "value": "and="
            }
          ]
        },
        {
          "type": "SYMBOL",
          "name": "expr_entry"
        }
      ]
    },
    "scope_stmt": {
      "type": "SEQ",
      "members": [
        {
          "type": "STRING",
          "value": "{"
        },
        {
          "type": "SYMBOL",
          "name": "_newline"
        },
        {
          "type": "REPEAT",
          "content": {
            "type": "SYMBOL",
            "name": "stmt"
          }
        },
        {
          "type": "STRING",
          "value": "}"
        }
      ]
    },
    "expr_entry": {
      "type": "SEQ",
      "members": [
        {
          "type": "CHOICE",
          "members": [
            {
              "type": "SYMBOL",
              "name": "expr_attr"
            },
            {
              "type": "BLANK"
            }
          ]
        },
        {
          "type": "SYMBOL",
          "name": "factor"
        },
        {
          "type": "REPEAT",
          "content": {
            "type": "SYMBOL",
            "name": "expr_cont"
          }
        },
        {
          "type": "CHOICE",
          "members": [
            {
              "type": "SYMBOL",
              "name": "in_range"
            },
            {
              "type": "BLANK"
            }
          ]
        },
        {
          "type": "CHOICE",
          "members": [
            {
              "type": "SYMBOL",
              "name": "is_typecase"
            },
            {
              "type": "BLANK"
            }
          ]
        }
      ]
    },
    "expr_cont": {
      "type": "CHOICE",
      "members": [
        {
          "type": "SEQ",
          "members": [
            {
              "type": "CHOICE",
              "members": [
                {
                  "type": "STRING",
                  "value": "++"
                },
                {
                  "type": "STRING",
                  "value": "+"
                },
                {
                  "type": "STRING",
                  "value": "-"
                },
                {
                  "type": "STRING",
                  "value": "*"
                },
                {
                  "type": "STRING",
                  "value": "/"
                },
                {
                  "type": "STRING",
                  "value": "|"
                },
                {
                  "type": "STRING",
                  "value": "&"
                },
                {
                  "type": "STRING",
                  "value": "^"
                },
                {
                  "type": "STRING",
                  "value": "or"
                },
                {
                  "type": "STRING",
                  "value": "and"
                },
                {
                  "type": "STRING",
                  "value": "has"
                },
                {
                  "type": "STRING",
                  "value": "implies"
                },
                {
                  "type": "STRING",
                  "value": "<<"
                },
                {
                  "type": "STRING",
                  "value": ">>"
                },
                {
                  "type": "STRING",
                  "value": "<"
                },
                {
                  "type": "STRING",
                  "value": "<="
                },
                {
                  "type": "STRING",
                  "value": "=="
                },
                {
                  "type": "STRING",
                  "value": "!="
                },
                {
                  "type": "STRING",
                  "value": ">="
                },
                {
                  "type": "STRING",
                  "value": ">"
                }
              ]
            },
            {
              "type": "SYMBOL",
              "name": "factor"
            }
          ]
        }
      ]
    },
    "is_typecase": {
      "type": "SEQ",
      "members": [
        {
          "type": "CHOICE",
          "members": [
            {
              "type": "STRING",
              "value": "is"
            },
            {
              "type": "STRING",
              "value": "implements"
            },
            {
              "type": "STRING",
              "value": "isnot"
            }
          ]
        },
        {
          "type": "SYMBOL",
          "name": "typecase"
        }
      ]
    },
    "in_range": {
      "type": "SEQ",
      "members": [
        {
          "type": "CHOICE",
          "members": [
            {
              "type": "STRING",
              "value": "in"
            },
            {
              "type": "STRING",
              "value": "notint"
            }
          ]
        },
        {
          "type": "CHOICE",
          "members": [
            {
              "type": "SYMBOL",
              "name": "bundle"
            },
            {
              "type": "SYMBOL",
              "name": "range"
            }
          ]
        }
      ]
    },
    "range": {
      "type": "SEQ",
      "members": [
        {
          "type": "SYMBOL",
          "name": "factor"
        },
        {
          "type": "CHOICE",
          "members": [
            {
              "type": "STRING",
              "value": "..<"
            },
            {
              "type": "STRING",
              "value": "..="
            },
            {
              "type": "STRING",
              "value": "..+"
            }
          ]
        },
        {
          "type": "SYMBOL",
          "name": "factor"
        },
        {
          "type": "CHOICE",
          "members": [
            {
              "type": "SEQ",
              "members": [
                {
                  "type": "STRING",
                  "value": "by"
                },
                {
                  "type": "SYMBOL",
                  "name": "factor"
                }
              ]
            },
            {
              "type": "BLANK"
            }
          ]
        }
      ]
    },
    "factor": {
      "type": "SEQ",
      "members": [
        {
          "type": "CHOICE",
          "members": [
            {
              "type": "CHOICE",
              "members": [
                {
                  "type": "STRING",
                  "value": "!"
                },
                {
                  "type": "STRING",
                  "value": "-"
                },
                {
                  "type": "STRING",
                  "value": "~"
                }
              ]
            },
            {
              "type": "BLANK"
            }
          ]
        },
        {
          "type": "CHOICE",
          "members": [
            {
              "type": "SYMBOL",
              "name": "factor_var_fcall_type"
            },
            {
              "type": "SYMBOL",
              "name": "literal"
            },
            {
              "type": "SYMBOL",
              "name": "bundle"
            },
            {
              "type": "SYMBOL",
              "name": "lambda_def"
            }
          ]
        }
      ]
    },
    "factor_var_fcall_type": {
      "type": "SEQ",
      "members": [
        {
          "type": "SYMBOL",
          "name": "variable_base"
        },
        {
          "type": "CHOICE",
          "members": [
            {
              "type": "CHOICE",
              "members": [
                {
                  "type": "SYMBOL",
                  "name": "fcall_args"
                },
                {
                  "type": "SYMBOL",
                  "name": "typecase"
                }
              ]
            },
            {
              "type": "BLANK"
            }
          ]
        }
      ]
    },
    "expr_attr": {
      "type": "SEQ",
      "members": [
        {
          "type": "CHOICE",
          "members": [
            {
              "type": "SEQ",
              "members": [
                {
                  "type": "STRING",
                  "value": "comptime"
                },
                {
                  "type": "CHOICE",
                  "members": [
                    {
                      "type": "STRING",
                      "value": "debug"
                    },
                    {
                      "type": "BLANK"
                    }
                  ]
                }
              ]
            },
            {
              "type": "STRING",
              "value": "debug"
            }
          ]
        }
      ]
    },
    "fcall_args": {
      "type": "SEQ",
      "members": [
        {
          "type": "SYMBOL",
          "name": "bundle"
        },
        {
          "type": "CHOICE",
          "members": [
            {
              "type": "SYMBOL",
              "name": "fcall_args_lambda"
            },
            {
              "type": "BLANK"
            }
          ]
        }
      ]
    },
    "fcall_args_lambda": {
      "type": "SEQ",
      "members": [
        {
          "type": "CHOICE",
          "members": [
            {
              "type": "SYMBOL",
              "name": "pipe_check"
            },
            {
              "type": "BLANK"
            }
          ]
        },
        {
          "type": "SYMBOL",
          "name": "lambda_def"
        },
        {
          "type": "CHOICE",
          "members": [
            {
              "type": "SYMBOL",
              "name": "fcall_args_lambda_else"
            },
            {
              "type": "BLANK"
            }
          ]
        }
      ]
    },
    "pipe_check": {
      "type": "CHOICE",
      "members": [
        {
          "type": "SEQ",
          "members": [
            {
              "type": "CHOICE",
              "members": [
                {
                  "type": "STRING",
                  "value": "pipe"
                },
                {
                  "type": "STRING",
                  "value": "async"
                }
              ]
            },
            {
              "type": "SYMBOL",
              "name": "bundle"
            }
          ]
        },
        {
          "type": "STRING",
          "value": "anypipe"
        }
      ]
    },
    "repipe_check": {
      "type": "SEQ",
      "members": [
        {
          "type": "CHOICE",
          "members": [
            {
              "type": "STRING",
              "value": "repipe"
            },
            {
              "type": "STRING",
              "value": "reasync"
            }
          ]
        },
        {
          "type": "SYMBOL",
          "name": "bundle"
        }
      ]
    },
    "fcall_args_lambda_else": {
      "type": "SEQ",
      "members": [
        {
          "type": "STRING",
          "value": "else"
        },
        {
          "type": "CHOICE",
          "members": [
            {
              "type": "SYMBOL",
              "name": "pipe_check"
            },
            {
              "type": "BLANK"
            }
          ]
        },
        {
          "type": "SYMBOL",
          "name": "lambda_def"
        }
      ]
    },
    "lambda_def": {
      "type": "SEQ",
      "members": [
        {
          "type": "STRING",
          "value": "{|"
        },
        {
          "type": "SYMBOL",
          "name": "lambda_def_constrains"
        },
        {
          "type": "CHOICE",
          "members": [
            {
              "type": "SEQ",
              "members": [
                {
                  "type": "SYMBOL",
                  "name": "_newline"
                },
                {
                  "type": "REPEAT",
                  "content": {
                    "type": "SYMBOL",
                    "name": "stmt"
                  }
                }
              ]
            },
            {
              "type": "SYMBOL",
              "name": "expr_entry"
            }
          ]
        },
        {
          "type": "STRING",
          "value": "}"
        }
      ]
    },
    "lambda_def_constrains": {
      "type": "SEQ",
      "members": [
        {
          "type": "CHOICE",
          "members": [
            {
              "type": "STRING",
              "value": "mut"
            },
            {
              "type": "BLANK"
            }
          ]
        },
        {
          "type": "CHOICE",
          "members": [
            {
              "type": "SEQ",
              "members": [
                {
                  "type": "STRING",
                  "value": "<"
                },
                {
                  "type": "SYMBOL",
                  "name": "argument_seq1"
                },
                {
                  "type": "STRING",
                  "value": ">"
                }
              ]
            },
            {
              "type": "BLANK"
            }
          ]
        },
        {
          "type": "CHOICE",
          "members": [
            {
              "type": "SEQ",
              "members": [
                {
                  "type": "STRING",
                  "value": "("
                },
                {
                  "type": "CHOICE",
                  "members": [
                    {
                      "type": "SYMBOL",
                      "name": "argument_seq1"
                    },
                    {
                      "type": "BLANK"
                    }
                  ]
                },
                {
                  "type": "STRING",
                  "value": ")"
                }
              ]
            },
            {
              "type": "BLANK"
            }
          ]
        },
        {
          "type": "CHOICE",
          "members": [
            {
              "type": "SEQ",
              "members": [
                {
                  "type": "STRING",
                  "value": "->"
                },
                {
                  "type": "STRING",
                  "value": "("
                },
                {
                  "type": "CHOICE",
                  "members": [
                    {
                      "type": "SYMBOL",
                      "name": "argument_seq1"
                    },
                    {
                      "type": "BLANK"
                    }
                  ]
                },
                {
                  "type": "STRING",
                  "value": ")"
                }
              ]
            },
            {
              "type": "BLANK"
            }
          ]
        },
        {
          "type": "CHOICE",
          "members": [
            {
              "type": "SYMBOL",
              "name": "where_modifier"
            },
            {
              "type": "BLANK"
            }
          ]
        },
        {
          "type": "STRING",
          "value": "|"
        }
      ]
    },
    "argument_seq1": {
      "type": "SEQ",
      "members": [
        {
          "type": "REPEAT",
          "content": {
            "type": "STRING",
            "value": ","
          }
        },
        {
          "type": "SEQ",
          "members": [
            {
              "type": "SYMBOL",
              "name": "argument"
            },
            {
              "type": "REPEAT",
              "content": {
                "type": "SEQ",
                "members": [
                  {
                    "type": "REPEAT1",
                    "content": {
                      "type": "STRING",
                      "value": ","
                    }
                  },
                  {
                    "type": "SYMBOL",
                    "name": "argument"
                  }
                ]
              }
            }
          ]
        },
        {
          "type": "REPEAT",
          "content": {
            "type": "STRING",
            "value": ","
          }
        }
      ]
    },
    "argument": {
      "type": "CHOICE",
      "members": [
        {
          "type": "SEQ",
          "members": [
            {
              "type": "SYMBOL",
              "name": "identifier"
            },
            {
              "type": "CHOICE",
              "members": [
                {
                  "type": "SYMBOL",
                  "name": "typecase"
                },
                {
                  "type": "BLANK"
                }
              ]
            }
          ]
        },
        {
          "type": "SYMBOL",
          "name": "typecase"
        }
      ]
    },
    "typecase": {
      "type": "SEQ",
      "members": [
        {
          "type": "STRING",
          "value": ":"
        },
        {
          "type": "CHOICE",
          "members": [
            {
              "type": "SEQ",
              "members": [
                {
                  "type": "CHOICE",
                  "members": [
                    {
                      "type": "SYMBOL",
                      "name": "variable_base"
                    },
                    {
                      "type": "SYMBOL",
                      "name": "bundle"
                    }
                  ]
                },
                {
                  "type": "CHOICE",
                  "members": [
                    {
                      "type": "SYMBOL",
                      "name": "where_modifier"
                    },
                    {
                      "type": "BLANK"
                    }
                  ]
                }
              ]
            },
            {
              "type": "BLANK"
            }
          ]
        }
      ]
    },
    "where_modifier": {
      "type": "SEQ",
      "members": [
        {
          "type": "STRING",
          "value": "where"
        },
        {
          "type": "STRING",
          "value": "{"
        },
        {
          "type": "CHOICE",
          "members": [
            {
              "type": "SEQ",
              "members": [
                {
                  "type": "SYMBOL",
                  "name": "_newline"
                },
                {
                  "type": "REPEAT",
                  "content": {
                    "type": "SYMBOL",
                    "name": "stmt"
                  }
                }
              ]
            },
            {
              "type": "SYMBOL",
              "name": "expr_entry"
            }
          ]
        },
        {
          "type": "STRING",
          "value": "}"
        }
      ]
    },
    "fcall_def": {
      "type": "SEQ",
      "members": [
        {
          "type": "STRING",
          "value": "|"
        },
        {
          "type": "CHOICE",
          "members": [
            {
              "type": "SEQ",
              "members": [
                {
                  "type": "STRING",
                  "value": "("
                },
                {
                  "type": "REPEAT",
                  "content": {
                    "type": "STRING",
                    "value": ","
                  }
                },
                {
                  "type": "REPEAT",
                  "content": {
                    "type": "SEQ",
                    "members": [
                      {
                        "type": "STRING",
                        "value": "$"
                      },
                      {
                        "type": "SYMBOL",
                        "name": "identifier"
                      },
                      {
                        "type": "REPEAT",
                        "content": {
                          "type": "STRING",
                          "value": ","
                        }
                      }
                    ]
                  }
                },
                {
                  "type": "STRING",
                  "value": ")"
                }
              ]
            },
            {
              "type": "BLANK"
            }
          ]
        },
        {
          "type": "STRING",
          "value": "|"
        },
        {
          "type": "SYMBOL",
          "name": "new_fun_scope"
        }
      ]
    },
    "new_fun_scope": {
      "type": "SEQ",
      "members": [
        {
          "type": "STRING",
          "value": "{"
        },
        {
          "type": "CHOICE",
          "members": [
            {
              "type": "SEQ",
              "members": [
                {
                  "type": "SYMBOL",
                  "name": "_newline"
                },
                {
                  "type": "REPEAT",
                  "content": {
                    "type": "SYMBOL",
                    "name": "stmt"
                  }
                }
              ]
            },
            {
              "type": "SYMBOL",
              "name": "expr_entry"
            }
          ]
        },
        {
          "type": "STRING",
          "value": "}"
        }
      ]
    },
    "variable_base": {
      "type": "SEQ",
      "members": [
        {
          "type": "SYMBOL",
          "name": "variable_base_start"
        },
        {
          "type": "REPEAT",
          "content": {
            "type": "SYMBOL",
            "name": "variable_base_field"
          }
        },
        {
          "type": "CHOICE",
          "members": [
            {
              "type": "SYMBOL",
              "name": "variable_prev_field"
            },
            {
              "type": "BLANK"
            }
          ]
        },
        {
          "type": "CHOICE",
          "members": [
            {
              "type": "SYMBOL",
              "name": "variable_base_last"
            },
            {
              "type": "BLANK"
            }
          ]
        }
      ]
    },
    "variable_base_start": {
      "type": "SEQ",
      "members": [
        {
          "type": "CHOICE",
          "members": [
            {
              "type": "SEQ",
              "members": [
                {
                  "type": "CHOICE",
                  "members": [
                    {
                      "type": "STRING",
                      "value": "$"
                    },
                    {
                      "type": "STRING",
                      "value": "%"
                    },
                    {
                      "type": "STRING",
                      "value": "#"
                    }
                  ]
                },
                {
                  "type": "CHOICE",
                  "members": [
                    {
                      "type": "SYMBOL",
                      "name": "identifier"
                    },
                    {
                      "type": "SYMBOL",
                      "name": "literal"
                    }
                  ]
                }
              ]
            },
            {
              "type": "SYMBOL",
              "name": "identifier"
            }
          ]
        }
      ]
    },
    "variable_base_field": {
      "type": "SEQ",
      "members": [
        {
          "type": "CHOICE",
          "members": [
            {
              "type": "STRING",
              "value": "?"
            },
            {
              "type": "BLANK"
            }
          ]
        },
        {
          "type": "CHOICE",
          "members": [
            {
              "type": "SYMBOL",
              "name": "dot_selector"
            },
            {
              "type": "SYMBOL",
              "name": "selector"
            }
          ]
        }
      ]
    },
    "variable_prev_field": {
      "type": "SEQ",
      "members": [
        {
          "type": "STRING",
          "value": "#["
        },
        {
          "type": "SYMBOL",
          "name": "_newline"
        },
        {
          "type": "SYMBOL",
          "name": "expr_entry"
        },
        {
          "type": "SYMBOL",
          "name": "_newline"
        },
        {
          "type": "STRING",
          "value": "]"
        }
      ]
    },
    "variable_base_last": {
      "type": "SEQ",
      "members": [
        {
          "type": "CHOICE",
          "members": [
            {
              "type": "STRING",
              "value": "?"
            },
            {
              "type": "REPEAT1",
              "content": {
                "type": "SYMBOL",
                "name": "variable_bit_sel"
              }
            }
          ]
        }
      ]
    },
    "dot_selector": {
      "type": "SEQ",
      "members": [
        {
          "type": "STRING",
          "value": "."
        },
        {
          "type": "CHOICE",
          "members": [
            {
              "type": "SYMBOL",
              "name": "identifier"
            },
            {
              "type": "SYMBOL",
              "name": "literal"
            }
          ]
        }
      ]
    },
    "selector": {
      "type": "SEQ",
      "members": [
        {
          "type": "STRING",
          "value": "["
        },
        {
          "type": "CHOICE",
          "members": [
            {
              "type": "SYMBOL",
              "name": "range"
            },
            {
              "type": "SYMBOL",
              "name": "expr_seq1"
            }
          ]
        },
        {
          "type": "CHOICE",
          "members": [
            {
              "type": "SYMBOL",
              "name": "_newline"
            },
            {
              "type": "BLANK"
            }
          ]
        },
        {
          "type": "STRING",
          "value": "]"
        }
      ]
    },
    "selector_empty": {
      "type": "SEQ",
      "members": [
        {
          "type": "STRING",
          "value": "["
        },
        {
          "type": "CHOICE",
          "members": [
            {
              "type": "CHOICE",
              "members": [
                {
                  "type": "SYMBOL",
                  "name": "range"
                },
                {
                  "type": "SYMBOL",
                  "name": "expr_seq1"
                }
              ]
            },
            {
              "type": "BLANK"
            }
          ]
        },
        {
          "type": "CHOICE",
          "members": [
            {
              "type": "SYMBOL",
              "name": "_newline"
            },
            {
              "type": "BLANK"
            }
          ]
        },
        {
          "type": "STRING",
          "value": "]"
        }
      ]
    },
    "expr_seq1": {
      "type": "SEQ",
      "members": [
        {
          "type": "REPEAT",
          "content": {
            "type": "STRING",
            "value": ","
          }
        },
        {
          "type": "SEQ",
          "members": [
            {
              "type": "SYMBOL",
              "name": "expr_entry"
            },
            {
              "type": "REPEAT",
              "content": {
                "type": "SEQ",
                "members": [
                  {
                    "type": "REPEAT1",
                    "content": {
                      "type": "STRING",
                      "value": ","
                    }
                  },
                  {
                    "type": "SYMBOL",
                    "name": "expr_entry"
                  }
                ]
              }
            }
          ]
        },
        {
          "type": "REPEAT",
          "content": {
            "type": "STRING",
            "value": ","
          }
        }
      ]
    },
    "bundle": {
      "type": "SEQ",
      "members": [
        {
          "type": "STRING",
          "value": "("
        },
        {
          "type": "CHOICE",
          "members": [
            {
              "type": "SEQ",
              "members": [
                {
                  "type": "CHOICE",
                  "members": [
                    {
                      "type": "SYMBOL",
                      "name": "bundle_seq1"
                    },
                    {
                      "type": "BLANK"
                    }
                  ]
                },
                {
                  "type": "CHOICE",
                  "members": [
                    {
                      "type": "SYMBOL",
                      "name": "_newline"
                    },
                    {
                      "type": "BLANK"
                    }
                  ]
                }
              ]
            },
            {
              "type": "SYMBOL",
              "name": "range"
            }
          ]
        },
        {
          "type": "STRING",
          "value": ")"
        }
      ]
    },
    "bundle_seq1": {
      "type": "SEQ",
      "members": [
        {
          "type": "REPEAT",
          "content": {
            "type": "STRING",
            "value": ","
          }
        },
        {
          "type": "SEQ",
          "members": [
            {
              "type": "SYMBOL",
              "name": "bundle_entry"
            },
            {
              "type": "REPEAT",
              "content": {
                "type": "SEQ",
                "members": [
                  {
                    "type": "REPEAT1",
                    "content": {
                      "type": "STRING",
                      "value": ","
                    }
                  },
                  {
                    "type": "SYMBOL",
                    "name": "bundle_entry"
                  }
                ]
              }
            }
          ]
        },
        {
          "type": "REPEAT",
          "content": {
            "type": "STRING",
            "value": ","
          }
        }
      ]
    },
    "bundle_entry": {
      "type": "SEQ",
      "members": [
        {
          "type": "SYMBOL",
          "name": "factor"
        },
        {
          "type": "CHOICE",
          "members": [
            {
              "type": "SEQ",
              "members": [
                {
                  "type": "STRING",
                  "value": "="
                },
                {
                  "type": "SYMBOL",
                  "name": "factor"
                }
              ]
            },
            {
              "type": "BLANK"
            }
          ]
        },
        {
          "type": "REPEAT",
          "content": {
            "type": "SYMBOL",
            "name": "expr_cont"
          }
        }
      ]
    },
    "variable_bit_sel": {
      "type": "SEQ",
      "members": [
        {
          "type": "STRING",
          "value": "@"
        },
        {
          "type": "CHOICE",
          "members": [
            {
              "type": "CHOICE",
              "members": [
                {
                  "type": "STRING",
                  "value": "sext"
                },
                {
                  "type": "STRING",
                  "value": "zext"
                },
                {
                  "type": "STRING",
                  "value": "|"
                },
                {
                  "type": "STRING",
                  "value": "&"
                },
                {
                  "type": "STRING",
                  "value": "^"
                },
                {
                  "type": "STRING",
                  "value": "+"
                }
              ]
            },
            {
              "type": "BLANK"
            }
          ]
        },
        {
          "type": "SYMBOL",
          "name": "selector_empty"
        }
      ]
    },
    "identifier": {
      "type": "TOKEN",
      "content": {
        "type": "PATTERN",
        "value": "[a-zA-Zα-ωΑ-Ωµ_][a-zA-Zα-ωΑ-Ωµ\\d_]*"
      }
    },
    "literal": {
      "type": "SYMBOL",
      "name": "integer"
    },
    "integer": {
      "type": "PATTERN",
      "value": "0[bB][01\\?](_?[01\\?])*|0[oO]?[0-7](_?[0-7])*|(0[dD])?\\d(_?\\d)*|0[xX][0-9a-fA-F](_?[0-9a-fA-F])*"
    },
    "string": {
      "type": "SEQ",
      "members": [
        {
          "type": "STRING",
          "value": "\""
        },
        {
          "type": "REPEAT",
          "content": {
            "type": "CHOICE",
            "members": [
              {
                "type": "IMMEDIATE_TOKEN",
                "content": {
                  "type": "PREC",
                  "value": 1,
                  "content": {
                    "type": "PATTERN",
                    "value": "[^\\\\\"\\n]+"
                  }
                }
              },
              {
                "type": "SYMBOL",
                "name": "_escape_sequence"
              }
            ]
          }
        },
        {
          "type": "STRING",
          "value": "\""
        }
      ]
    },
    "_escape_sequence": {
      "type": "TOKEN",
      "content": {
        "type": "PREC",
        "value": 1,
        "content": {
          "type": "SEQ",
          "members": [
            {
              "type": "STRING",
              "value": "\\"
            },
            {
              "type": "CHOICE",
              "members": [
                {
                  "type": "PATTERN",
                  "value": "[^xuU]"
                },
                {
                  "type": "PATTERN",
                  "value": "\\d{2,3}"
                },
                {
                  "type": "PATTERN",
                  "value": "x[0-9a-fA-F]{2,}"
                },
                {
                  "type": "PATTERN",
                  "value": "u[0-9a-fA-F]{4}"
                },
                {
                  "type": "PATTERN",
                  "value": "U[0-9a-fA-F]{8}"
                }
              ]
            }
          ]
        }
      }
    },
    "constant": {
      "type": "CHOICE",
      "members": [
        {
          "type": "SYMBOL",
          "name": "integer"
        },
        {
          "type": "SYMBOL",
          "name": "string"
        }
      ]
    },
    "_newline": {
      "type": "REPEAT1",
      "content": {
        "type": "CHOICE",
        "members": [
          {
            "type": "PATTERN",
            "value": ";"
          },
          {
            "type": "PATTERN",
            "value": "\\n"
          },
          {
            "type": "PATTERN",
            "value": "\\\\\\r?\\n"
          }
        ]
      }
    },
    "comment": {
      "type": "TOKEN",
      "content": {
        "type": "SEQ",
        "members": [
          {
            "type": "STRING",
            "value": "//"
          },
          {
            "type": "PATTERN",
            "value": ".*"
          }
        ]
      }
    }
  },
  "extras": [
    {
      "type": "PATTERN",
      "value": " "
    },
    {
      "type": "PATTERN",
      "value": "\\t"
    },
    {
      "type": "SYMBOL",
      "name": "comment"
    }
  ],
  "conflicts": [],
  "externals": [],
  "inline": [],
  "supertypes": []
}

